xqt/common.py
xqt/errors.py
xqt/lazyload.py
xqt/pyi_hook.py
xqt/_version.py
xqt/__init__.py
xqt/core/__init__.py
xqt/gui/xfiledialog.py
xqt/gui/__init__.py
xqt/wrappers/pyqt4.py
xqt/wrappers/pyside.py
xqt/wrappers/__init__.py
xqt-2015.0.4.dist-info/DESCRIPTION.rst
xqt-2015.0.4.dist-info/METADATA
xqt-2015.0.4.dist-info/metadata.json
xqt-2015.0.4.dist-info/RECORD
xqt-2015.0.4.dist-info/top_level.txt
xqt-2015.0.4.dist-info/WHEEL
