Metadata-Version: 2.0
Name: xqt
Version: 2015.0.4
Summary: Wrapper system to handle differences between Python Qt ports.
Home-page: https://github.com/ProjexSoftware/xqt
Author: Eric Hulser
Author-email: eric.hulser@gmail.com
License: LGPL
Platform: UNKNOWN
Requires-Dist: projex
